{
  "serviceId": "1903918561",
  "idx": 154,
  "billed": false,
  "inventory": {
    "rowNumber": 155,
    "billingName": "K S BATTH & G S BATTH PARTNERSHIP",
    "actualOwner": null,
    "account": "1909940814-8",
    "serviceId": "1903918561",
    "meterSerial": "1010785955",
    "growerPumpId": null,
    "rateSchedule": "HAGC",
    "legacy": null,
    "descriptor": null,
    "latitude": 36.52711,
    "longitude": -119.83773,
    "hasCoordinates": true,
    "solarFlag": false,
    "solarGroupLabel": null,
    "solarKw": null,
    "nemType": null,
    "trueUpMonth": null,
    "contiguous": null,
    "solarNotes": null,
    "gpm": null,
    "crop": null,
    "installedOn": null,
    "irrigation": null,
    "ranch": null,
    "status": null
  },
  "billing": null,
  "summaries": [],
  "nem": null
}
